orgjax/pyjit/__init__.py
orgjax/pyjit/activities.py
orgjax/pyjit/auth.py
orgjax/pyjit/client.py
orgjax/pyjit/dao.py
orgjax/pyjit/geo.py
orgjax/pyjit/model/__init__.py
orgjax/pyjit/model/convert.py
orgjax/pyjit/model/crop.py
orgjax/pyjit/templates.py
orgjax/pyjit/worker.py
jax_pyjit-0.3.7.dist-info/METADATA
jax_pyjit-0.3.7.dist-info/WHEEL
jax_pyjit-0.3.7.dist-info/licenses/LICENSE.txt
jax_pyjit-0.3.7.dist-info/RECORD
