Metadata-Version: 2.4
Name: jax-pyjit
Version: 0.3.7
Summary: JIT python bindings including the client and data access objects
License: Apache-2.0
License-File: LICENSE.txt
Author: Matthew Gerring
Author-email: matthew.gerring@jax.org
Requires-Python: >=3.10,<4.0
Classifier: License :: OSI Approved :: Apache Software License
Classifier: Programming Language :: Python :: 3
Classifier: Programming Language :: Python :: 3.10
Classifier: Programming Language :: Python :: 3.11
Classifier: Programming Language :: Python :: 3.12
Classifier: Programming Language :: Python :: 3.13
Classifier: Programming Language :: Python :: 3.14
Requires-Dist: auth0-python (>=4.13.0,<5.0.0)
Requires-Dist: cryptography (>=46.0.3,<47.0.0)
Requires-Dist: dataclasses-json (>=0.6.7,<0.7.0)
Requires-Dist: geopandas (>=1.1.1,<2.0.0)
Requires-Dist: jax-cs-storage (>=0.10.0,<0.11.0)
Requires-Dist: requests (>=2.32.5,<3.0.0)
Requires-Dist: temporalio (>=1.18.0,<2.0.0)
Requires-Dist: typer (>=0.20.0,<0.21.0)
